criticalityMaps/__init__.py
criticalityMaps/criticality/__init__.py
criticalityMaps/criticality/core.py
criticalityMaps/criticality/criticality_functions.py
criticalityMaps/criticality/mp_queue_tools.py
criticalityMaps/mapping/__init__.py
criticalityMaps/mapping/criticality_map.py
criticalityMaps/mapping/df_map.py
criticalityMaps/mapping/geojson_handler.py
criticalityMaps-0.1.0.dist-info/METADATA
criticalityMaps-0.1.0.dist-info/WHEEL
criticalityMaps-0.1.0.dist-info/license.txt
criticalityMaps-0.1.0.dist-info/top_level.txt
criticalityMaps-0.1.0.dist-info/RECORD
