Metadata-Version: 2.1
Name: criticalityMaps
Version: 0.1.0
Summary: WNTR utility for generating criticality maps
Home-page: https://github.com/pshassett/CriticalityMaps
Author: Patrick Hassett
Maintainer-email: pshassett@humboldt.edu
License: MIT
Platform: UNKNOWN
Requires-Dist: networkx
Requires-Dist: pandas
Requires-Dist: numpy
Requires-Dist: scipy
Requires-Dist: matplotlib
Requires-Dist: plotly
Requires-Dist: wntr
Requires-Dist: pyyaml
Requires-Dist: utm
Requires-Dist: jinja2
Requires-Dist: six
